aws_lambda_sls/__init__.py
aws_lambda_sls/app.py
aws_lambda_sls/awsclient.py
aws_lambda_sls/cli.py
aws_lambda_sls/compat.py
aws_lambda_sls/constants.py
aws_lambda_sls/deploy.py
aws_lambda_sls/factory.py
aws_lambda_sls/invoke.py
aws_lambda_sls/local.py
aws_lambda_sls/models.py
aws_lambda_sls/monitor.py
aws_lambda_sls/package.py
aws_lambda_sls/signals.py
aws_lambda_sls/utils.py
aws_lambda_sls-0.1.0.dist-info/METADATA
aws_lambda_sls-0.1.0.dist-info/RECORD
aws_lambda_sls-0.1.0.dist-info/WHEEL
aws_lambda_sls-0.1.0.dist-info/entry_points.txt
aws_lambda_sls-0.1.0.dist-info/top_level.txt
