Metadata-Version: 2.1
Name: aws-lambda-sls
Version: 0.1.0
Summary: Python Simple Serverless for AWS Lambda Project. 
Home-page: https://github.com/dwpy/aws-lambda-sls
Author: Dongwei
License: BSD
Project-URL: Code, https://github.com/dwpy/aws-lambda-sls
Platform: any
Classifier: Development Status :: 1 - Planning
Classifier: Environment :: Web Environment
Classifier: Intended Audience :: Developers
Classifier: License :: OSI Approved :: BSD License
Classifier: Operating System :: OS Independent
Classifier: Programming Language :: Python :: 3.4
Classifier: Programming Language :: Python :: 3.5
Classifier: Programming Language :: Python :: 3.6
Classifier: Programming Language :: Python :: 3.7
Requires-Python: >=3.4
Requires-Dist: click
Requires-Dist: boto3
Requires-Dist: botocore
Requires-Dist: six
Requires-Dist: pip (<=18,>=9)
Requires-Dist: attrs
Requires-Dist: importreqs
Requires-Dist: kombu
Requires-Dist: blinker
